yoloCarAccident/__init__.py
yoloCarAccident/yoloCarAccident.py
yoloCarAccident-0.0.1.dist-info/METADATA
yoloCarAccident-0.0.1.dist-info/RECORD
yoloCarAccident-0.0.1.dist-info/WHEEL
yoloCarAccident-0.0.1.dist-info/top_level.txt
