Metadata-Version: 2.1
Name: yoloCarAccident
Version: 0.0.1
Summary: yoloCarAccident Helper
Home-page: https://github.com/Ayush21298/ITRI/tree/master/yoloCarAccident
Author: Ayush21298
Author-email: patel.ayush08@gmail.com
License: UNKNOWN
Platform: UNKNOWN
Classifier: Programming Language :: Python :: 2
Classifier: License :: OSI Approved :: MIT License
Classifier: Operating System :: OS Independent
